README.rst
setup.py
alembic/env.py
moodlefuse/__init__.py
moodlefuse/__main__.py
moodlefuse/configure.py
moodlefuse/core.py
moodlefuse/exception.py
moodlefuse/helpers.py
moodlefuse/model_manager.py
moodlefuse/services.py
moodlefuse.egg-info/PKG-INFO
moodlefuse.egg-info/SOURCES.txt
moodlefuse.egg-info/dependency_links.txt
moodlefuse.egg-info/entry_points.txt
moodlefuse.egg-info/not-zip-safe
moodlefuse.egg-info/requires.txt
moodlefuse.egg-info/top_level.txt
moodlefuse/filesystem/__init__.py
moodlefuse/filesystem/file_operations.py
moodlefuse/filesystem/file_system_translator.py
moodlefuse/filesystem/path_parser.py
moodlefuse/filesystem/remote_handler.py
moodlefuse/filesystem/files/__init__.py
moodlefuse/filesystem/files/cache_file.py
moodlefuse/filesystem/files/directory.py
moodlefuse/filesystem/files/file.py
moodlefuse/models/__init__.py
moodlefuse/models/users/__init__.py
moodlefuse/models/users/models.py
moodlefuse/moodle/__init__.py
moodlefuse/moodle/api.py
moodlefuse/moodle/attributes.py
moodlefuse/moodle/exception.py
moodlefuse/moodle/handler.py
moodlefuse/moodle/parser.py
moodlefuse/moodle/paths.py
moodlefuse/moodle/scraper.py
moodlefuse/moodle/assignments/__init__.py
moodlefuse/moodle/assignments/assignment_errors.py
moodlefuse/moodle/assignments/assignment_grader.py
moodlefuse/moodle/assignments/assignment_handler.py
moodlefuse/moodle/assignments/assignment_parser.py
moodlefuse/moodle/courses/__init__.py
moodlefuse/moodle/courses/course_errors.py
moodlefuse/moodle/courses/course_handler.py
moodlefuse/moodle/courses/course_parser.py
moodlefuse/moodle/emulator/__init__.py
moodlefuse/moodle/emulator/core_emulator.py
moodlefuse/moodle/emulator/emulator.py
moodlefuse/moodle/emulator/js_enabled_emulator.py
moodlefuse/moodle/forums/__init__.py
moodlefuse/moodle/forums/forum_handler.py
moodlefuse/moodle/forums/forum_parser.py
moodlefuse/moodle/resources/__init__.py
moodlefuse/moodle/resources/resource_errors.py
moodlefuse/moodle/resources/resource_handler.py
moodlefuse/moodle/resources/resource_parser.py
tests/__init__.py
tests/assignment_tests.py
tests/courses_category_tests.py
tests/courses_tests.py
tests/filesystem_tests.py
tests/resources_tests.py
tests/utils.py
tests/courses/__init__.py
