Metadata-Version: 1.1
Name: moodlefuse
Version: 0.3.0
Summary: FUSE filesystem based on moodle implementation
Home-page: http://github.com/brogand1993/MoodleFUSE
Author: Darren Brogan
Author-email: darren.brogan2@mail.dcu.ie
License: MIT License
Platform: UNKNOWN
Classifier: Development Status :: 3 - Alpha
Classifier: Environment :: Console
Classifier: Operating System :: OS Independent
Classifier: Programming Language :: Python
Classifier: Topic :: Utilities
Classifier: Programming Language :: Python :: 2.7
